brother_label/__init__.py
brother_label/cli.py
brother_label/converter.py
brother_label/core.py
brother_label/devices.py
brother_label/engine.py
brother_label/exceptions.py
brother_label/labels.py
brother_label/raster.py
brother_label/reader.py
brother_label/backends/__init__.py
brother_label/backends/generic.py
brother_label/backends/linux_kernel.py
brother_label/backends/network.py
brother_label/backends/pyusb.py
brother_label-2.0a8.dist-info/LICENSE
brother_label-2.0a8.dist-info/METADATA
brother_label-2.0a8.dist-info/WHEEL
brother_label-2.0a8.dist-info/entry_points.txt
brother_label-2.0a8.dist-info/top_level.txt
brother_label-2.0a8.dist-info/RECORD
