Metadata-Version: 2.1
Name: brother-label
Version: 2.0a8
Summary: Brother label printer interface for QL and PT series printers.
Author-email: Philipp Klaus <philipp.l.klaus@web.de>, Dean Gardiner <me@dgardiner.net>
License: GPL
Project-URL: repository, https://github.com/fuzeman/brother-label
Keywords: Brother,QL-500,QL-550,QL-560,QL-570,QL-580N,QL-600,QL-650TD,QL-700,QL-710W,QL-720NW,QL-800,QL-810W,QL-820NWB,QL-1050,QL-1060N,QL-1100,QL-1100NWB,QL-1115NWB,PT-P750W,PT-P900W,PT-P950NW,PT-E550W
Classifier: Development Status :: 4 - Beta
Classifier: Operating System :: OS Independent
Classifier: License :: OSI Approved :: GNU General Public License v3 or later (GPLv3+)
Classifier: Programming Language :: Python
Classifier: Programming Language :: Python :: 3
Classifier: Topic :: Scientific/Engineering :: Visualization
Classifier: Topic :: System :: Hardware :: Hardware Drivers
License-File: LICENSE
Requires-Dist: click
Requires-Dist: future
Requires-Dist: packbits
Requires-Dist: pillow >=3.3.0
Requires-Dist: pyusb
Requires-Dist: attrs
Requires-Dist: enum34 ; python_version < "3.4"
Requires-Dist: typing ; python_version < "3.5"
